deeper_rpg-0.2.0.dist-info/METADATA
deeper_rpg-0.2.0.dist-info/WHEEL
deeper_rpg-0.2.0.dist-info/entry_points.txt
deeper_rpg-0.2.0.dist-info/license_files/LICENSE
deeper/database/utils.py
deeper/database/database.py
deeper/database/__init__.py
deeper/widgets/component/entity_layer.py
deeper/widgets/component/block_widget.py
deeper/widgets/component/component_widget.py
deeper/widgets/component/sprite_vu_widget.py
deeper/widgets/component/sprite_animation_widget.py
deeper/widgets/component/__init__.py
deeper/widgets/component/entity_bp_widget.py
deeper/widgets/component/component_window.py
deeper/widgets/metrics_window.py
deeper/widgets/camera_window.py
deeper/widgets/dragger.py
deeper/widgets/tool/tool_widget.py
deeper/widgets/tool/__init__.py
deeper/widgets/state/snap_option.py
deeper/widgets/state/__init__.py
deeper/widgets/blueprint_window.py
deeper/widgets/icon.py
deeper/widgets/menu.py
deeper/widgets/layers_window.py
deeper/widgets/selectable.py
deeper/widgets/button.py
deeper/widgets/catalog_window.py
deeper/widgets/blueprint/blueprint_widget.py
deeper/widgets/blueprint/sprite_vu_bp_widget.py
deeper/widgets/blueprint/block_bp_widget.py
deeper/widgets/blueprint/sprite_animation_bp_widget.py
deeper/widgets/blueprint/__init__.py
deeper/widgets/entity_window.py
deeper/widgets/setting/vec3_widget.py
deeper/widgets/setting/drag_wrapper.py
deeper/widgets/setting/drop_wrapper.py
deeper/widgets/setting/vec2_widget.py
deeper/widgets/setting/bool_widget.py
deeper/widgets/setting/setting_widget.py
deeper/widgets/setting/int_widget.py
deeper/widgets/setting/setting_group_widget.py
deeper/widgets/setting/float_widget.py
deeper/widgets/setting/string_widget.py
deeper/widgets/setting/__init__.py
deeper/widgets/toolbar.py
deeper/widgets/__init__.py
deeper/model.py
deeper/deeper.pyi
deeper/window.py
deeper/levels/basic_level.py
deeper/levels/__init__.py
deeper/view.py
deeper/__about__.py
deeper/blueprint.py
deeper/tool.py
deeper/ecs/component.py
deeper/ecs/py.typed
deeper/ecs/entity.py
deeper/ecs/__init__.py
deeper/kits/blueprint_kit.py
deeper/kits/setting_widget_kit.py
deeper/kits/blueprint_widget_kit.py
deeper_rpg-0.2.0.dist-info/RECORD
