Metadata-Version: 2.1
Name: deeper-rpg
Version: 0.2.0
Classifier: Development Status :: 4 - Beta
Classifier: Programming Language :: Rust
Classifier: Programming Language :: Python
Classifier: Programming Language :: Python :: 3.8
Classifier: Programming Language :: Python :: 3.9
Classifier: Programming Language :: Python :: 3.10
Classifier: Programming Language :: Python :: Implementation :: CPython
Classifier: Programming Language :: Python :: Implementation :: PyPy
Requires-Dist: arcade ==3.0.0.dev15
Requires-Dist: PyGLM ~=2.7.0
Requires-Dist: imgui ~=1.4.1
Requires-Dist: pyyaml ~=6.0
Requires-Dist: loguru ~=0.6.0
Requires-Dist: pydantic ~=1.10.6
Requires-Dist: sqlalchemy ~=2.0.5.post1
Requires-Dist: click ~=8.1.3
Requires-Dist: pytest ~=7.2.1; extra == 'test'
Requires-Dist: maturin ~=0.14.7; extra == 'dev'
Requires-Dist: black ~=22.12.0; extra == 'dev'
Provides-Extra: test
Provides-Extra: dev
License-File: LICENSE
Summary: Dungeon RPG with Python Arcade and Rust
Keywords: 
Author-email: Kurtis Fields <kurtisfields@gmail.com>
Requires-Python: >=3.8
Project-URL: documentation, https://kfields.github.io/deeper/
Project-URL: changelog, https://github.com/kfields/deeper/blob/main/CHANGELOG.md
Project-URL: homepage, https://github.com/kfields/deeper
Project-URL: repository, https://github.com/kfields/deeper
